{
  "ui_id":"_sld",
  "language":"en_US",
  "share":{
    "enabled":false,
    "discount":true,
    "buttonTextOnRegular":"Share your photo product!",
    "buttonTextOnDiscount":"Share & Get 80% Discount!"
  },
  "fitToRatio":{
    "useDefaultApi":false,
    "rules":[
      {
        "ratio":"1.0",
        "id":"SDKPIXDEMO03"
      }
    ]
  },
  "GA_ID":"UA-55216316-15",
  "marketingData":{
    "sideBarData" : {
      "p_side_banner_top_title": "Photo Gifts",
      "p_side_banner_top_sub_title": "Summer Sale Special",
      "p_side_banner_bottom_title": "Your Photos on Products",
      "p_side_banner_bottom_sub_title": "FREE SHIPPING!"
    },
    "ossEnabled":false,
    "ossMessage":"",
    "ossData":[
      {
        "tmbWidth":120,
        "tmbHeight":120,
        "h2":"<p class='oss_product_price'<span>[currency][price]</span></p><p class='oss_product_name'>4 Premium Magnets</p><p class='oss_special_offer'>40% off & free shipping</p>",
        "titleStyle":"",
        "p":"",
        "pStyle":"display:none;",
        "productImage":"pixter_magnet_square_oss.png",
        "index":0,
        "PID":"MAGN030304EEEE",
        "portholeStyle":"top: 112px;left: 340px;",
        "checkoutStyle":"preview",
        "buttonText":"Continue"
      },
      {
        "tmbWidth":190,
        "tmbHeight":190,
        "h2":"<p class='oss_product_price'>[currency][price]</p><p class='oss_product_name'>10 Flat Cards</p><p class='oss_special_offer'>40% off & free shipping</p>",
        "titleStyle":"",
        "p":"",
        "pStyle":"display:none;",
        "productImage":"pixter_flatcard_square_oss.png",
        "index":1,
        "PID":"FLAT050510EEEE",
        "portholeStyle":"left: 328px;top: 66px;transform: rotateZ(-13deg);",
        "checkoutStyle":"preview",
        "buttonText":"Continue"
      },
      {
        "tmbWidth":109,
        "tmbHeight":109,
        "h2":"White T-Shirt <span>[currency][price]</span>",
        "titleStyle":"width: 250px; top: 10px; background: rgba(0,0,0,0.4); font-size: 28px;  height: 38px; line-height: 38px; text-align: center;",
        "p":"<span>40% OFF</span> & FREE SHIPPING",
        "pStyle":"top: 68px; background: rgba(0, 0, 0, 0.4); font-size: 19px; width: 260px; height: 27px; line-height: 27px; text-align: center; padding: 0px 15px 10px;",
        "productImage":"pixter_tshirt_oss.png",
        "index":5,
        "PID":"TSHIRTCOTLARGT",
        "portholeStyle":"left: 370px;top: 110px;",
        "checkoutStyle":"preview",
        "buttonText":"Choose T-Shirt Size"
      }   ,
      {
        "tmbWidth":206,
        "tmbHeight":206,
        "h2":"<p class='oss_product_price'>[currency][price]</p><p class='oss_product_name'>Beautiful Canvas</p><p class='oss_special_offer'>40% off</p>",
        "titleStyle":"",
        "p":"",
        "pStyle":"display:none;",
        "productImage":"pixter_canvas_square_oss.png",
        "index":3,
        "PID":"CNVS101001CWB9",
        "portholeStyle":"left: 370px;top: 24px",
        "checkoutStyle":"preview",
        "buttonText":"Continue"
      },
      {
        "tmbWidth":210,
        "tmbHeight":210,
        "h2":"<p class='oss_product_price'>[currency][price]</p><p class='oss_product_name'>Ceramic Mug</p><p class='oss_special_offer'>40% off & free shipping</p>",
        "titleStyle":"",
        "p":"",
        "pStyle":"display:none;",
        "productImage":"pixter_mug_oss.png",
        "index":4,
        "PID":"CMUG11OZSQRMUG",
        "portholeStyle":"left: 270px;top: 92px;",
        "checkoutStyle":"preview",
        "buttonText":"Continue"
      },
      {
        "tmbWidth":107,
        "tmbHeight":107,
        "h2":"<p class='oss_product_price'>[currency][price]</p><p class='oss_product_name'>Tote Bag</p><p class='oss_special_offer'>40% off & free shipping</p>",
        "titleStyle":"",
        "p":"",
        "pStyle":"display:none;",
        "productImage":"pixter_toteBag_oss.png",
        "index":5,
        "PID":"TTE12X12TOTE10",
        "portholeStyle":"top: 150px;left: 355px;",
        "checkoutStyle":"preview",
        "buttonText":"Continue"
      }
    ]
  },
  "specialOffer":{
    "startDate":"2014-10-12",
    "endDate":"2017-12-01",
    "catalog":"Summer Sale Special - <span class='colorizedSpan'>40% OFF</span> on <span class='colorizedSpan'>all products</span>",
    "product_MAGN030304EEEE":"Enjoy <span class='colorizedSpan'>40% OFF</span> & <span class='colorizedSpan'>FREE Shipping</span> of your Product! <span class='smallerSpan'>(applied on checkout)</span>",
    "product_FLAT050510EEEE":"Enjoy <span class='colorizedSpan'>40% OFF</span> & <span class='colorizedSpan'>FREE Shipping</span> of your Product! <span class='smallerSpan'>(applied on checkout)</span>",
    "product_CNVS141401CWB8":"Enjoy <span class='colorizedSpan'>40% Off</span> on your product <span class='smallerSpan'>(applied on checkout)</span>",
    "product_CNVS101001CWB9":"Enjoy <span class='colorizedSpan'>40% Off</span> on your product <span class='smallerSpan'>(applied on checkout)</span>",
    "product_TSHIRTCOTXXLTT":"Enjoy <span class='colorizedSpan'>40% OFF</span> & <span class='colorizedSpan'>FREE Shipping</span> of your Product! <span class='smallerSpan'>(applied on checkout)</span>",
    "product_TSHIRTCOTXLTTT":"Enjoy <span class='colorizedSpan'>40% OFF</span> & <span class='colorizedSpan'>FREE Shipping</span> of your Product! <span class='smallerSpan'>(applied on checkout)</span>",
    "product_TSHIRTCOTSMALT":"Enjoy <span class='colorizedSpan'>40% OFF</span> & <span class='colorizedSpan'>FREE Shipping</span> of your Product! <span class='smallerSpan'>(applied on checkout)</span>",
    "product_TSHIRTCOTMEDUT":"Enjoy <span class='colorizedSpan'>40% OFF</span> & <span class='colorizedSpan'>FREE Shipping</span> of your Product! <span class='smallerSpan'>(applied on checkout)</span>",
    "product_TSHIRTCOTLARGT":"Enjoy <span class='colorizedSpan'>40% OFF</span> & <span class='colorizedSpan'>FREE Shipping</span> of your Product! <span class='smallerSpan'>(applied on checkout)</span>",
    "product_CMUG11OZSQRMUG":"Enjoy <span class='colorizedSpan'>40% OFF</span> & <span class='colorizedSpan'>FREE Shipping</span> of your Product! <span class='smallerSpan'>(applied on checkout)</span>",
    "product_TTE12X12TOTE10":"Enjoy <span class='colorizedSpan'>40% OFF</span> & <span class='colorizedSpan'>FREE Shipping</span> of your Product! <span class='smallerSpan'>(applied on checkout)</span>",
    "selfInitiate":{
      "couponString":"FD40FREES",
      "product_MAGN030304EEEE":{"couponString":"FD40FREES","newPrice":"$4.19"},
      "product_FLAT050510EEEE":{"couponString":"FD40FREES","newPrice":"$8.99"},
      "product_CNVS101001CWB9":{"couponString":"FD40OFFS","newPrice":"$22.19"},
      "product_CNVS141401CWB8":{"couponString":"FD40OFFS","newPrice":"$31.79"},
      "product_TSHIRTCOTXXLTT":{"couponString":"FD40FREES","newPrice":"$8.99"},
      "product_TSHIRTCOTXLTTT":{"couponString":"FD40FREES","newPrice":"$8.99"},
      "product_TSHIRTCOTSMALT":{"couponString":"FD40FREES","newPrice":"$8.99"},
      "product_TSHIRTCOTMEDUT":{"couponString":"FD40FREES","newPrice":"$8.99"},
      "product_TSHIRTCOTLARGT":{"couponString":"FD40FREES","newPrice":"$8.99"},
      "product_CMUG11OZSQRMUG":{"couponString":"FD40FREES","newPrice":"$5.39"},
      "product_TTE12X12TOTE10":{"couponString":"FD40FREES","newPrice":"$17.99"}
    }
  }
}